pickups/basepickup.py
pickups/helpers.py
pickups/log.py
pickups/sampleconfig.cfg
pickups/_package.py
pickups/__init__.py
pickups/bamboo/bamboopickup.py
pickups/bamboo/__init__.py
pickups/feedback/basefeedback.py
pickups/feedback/__init__.py
pickups/feedback/energenie/egpms.py
pickups/feedback/energenie/__init__.py
pickups-0.8.0.dist-info/DESCRIPTION.rst
pickups-0.8.0.dist-info/METADATA
pickups-0.8.0.dist-info/metadata.json
pickups-0.8.0.dist-info/RECORD
pickups-0.8.0.dist-info/top_level.txt
pickups-0.8.0.dist-info/WHEEL
