Metadata-Version: 2.0
Name: pickups
Version: 0.8.0
Summary: Pickups delivers all neccessary tools to run Atlassian Bamboo with RasberryPi based extreme feedback devices
Home-page: https://github.com/maiksensi/pickups/
Author: Maik Figura
Author-email: maiksensi[at]gmail.com
License: MIT
Keywords: pickups
Platform: UNKNOWN
Classifier: Development Status :: 4 - Beta
Classifier: Intended Audience :: Developers
Classifier: License :: OSI Approved :: MIT License
Classifier: Natural Language :: English
Classifier: Programming Language :: Python :: 2.7
Classifier: Programming Language :: Python :: 3.4
Requires-Dist: requests
